{"track":"nemuno_ziedas-fastlap","number_of_sessions":1,"players":[{"name":"2m","car":"ktm_xbow_r","skin":"14_isotope_green_11"},{"name":"Michael Martin","car":"ktm_xbow_r","skin":"07_dark_grey_09"},{"name":"Mohammed Al-Qassimi","car":"ktm_xbow_r","skin":"10_blue_02"},{"name":"Max Saarinen","car":"ktm_xbow_r","skin":"03_dark_grey_06"},{"name":"Jeff LeBeau","car":"ktm_xbow_r","skin":"04_yellow_07"},{"name":"Eerik Tuohino","car":"ktm_xbow_r","skin":"08_orange_19"},{"name":"Alain Camilli","car":"ktm_xbow_r","skin":"02_isotope_green_10"},{"name":"Bernard Bensimon","car":"ktm_xbow_r","skin":"12_cyan_05"},{"name":"Romain Rouhaud","car":"ktm_xbow_r","skin":"16_light_grey_13"},{"name":"Philippe Jamoul","car":"ktm_xbow_r","skin":"01_blue_01"},{"name":"Giorgio Chiarcossi","car":"ktm_xbow_r","skin":"13_light_grey_08"}],"sessions":[{"event":0,"name":"Quick Race","type":3,"lapsCount":10,"duration":0,"laps":[{"lap":0,"car":0,"sectors":[46203,25911,20947],"time":93061,"cuts":0,"tyre":"SM"},{"lap":1,"car":0,"sectors":[34264,26014,21065],"time":81343,"cuts":0,"tyre":"SM"},{"lap":2,"car":0,"sectors":[32351,26047,20767],"time":79165,"cuts":0,"tyre":"SM"},{"lap":3,"car":0,"sectors":[31722,25686,21033],"time":78441,"cuts":0,"tyre":"SM"},{"lap":4,"car":0,"sectors":[31990,25483,21456],"time":78929,"cuts":0,"tyre":"SM"},{"lap":5,"car":0,"sectors":[31727,25434,20831],"time":77992,"cuts":0,"tyre":"SM"},{"lap":6,"car":0,"sectors":[31456,25308,21370],"time":78134,"cuts":0,"tyre":"SM"},{"lap":7,"car":0,"sectors":[31367,26141,20956],"time":78464,"cuts":0,"tyre":"SM"},{"lap":8,"car":0,"sectors":[31336,26194,21133],"time":78663,"cuts":0,"tyre":"SM"},{"lap":9,"car":0,"sectors":[31185,24997,20551],"time":76733,"cuts":0,"tyre":"SM"},{"lap":0,"car":1,"sectors":[43322,25988,21839],"time":91149,"cuts":0,"tyre":"SM"},{"lap":1,"car":1,"sectors":[36008,27356,22991],"time":86355,"cuts":0,"tyre":"SM"},{"lap":2,"car":1,"sectors":[35968,27202,22150],"time":85320,"cuts":0,"tyre":"SM"},{"lap":3,"car":1,"sectors":[35847,27117,22090],"time":85054,"cuts":0,"tyre":"SM"},{"lap":4,"car":1,"sectors":[35771,27068,22037],"time":84876,"cuts":0,"tyre":"SM"},{"lap":5,"car":1,"sectors":[35703,27035,22014],"time":84752,"cuts":0,"tyre":"SM"},{"lap":6,"car":1,"sectors":[35652,26964,21968],"time":84584,"cuts":0,"tyre":"SM"},{"lap":7,"car":1,"sectors":[35598,26914,21951],"time":84463,"cuts":0,"tyre":"SM"},{"lap":8,"car":1,"sectors":[35610,26900,22235],"time":84745,"cuts":0,"tyre":"SM"},{"lap":9,"car":1,"sectors":[35560,26959,21979],"time":84498,"cuts":0,"tyre":"SM"},{"lap":0,"car":2,"sectors":[46945,26077,21574],"time":94596,"cuts":0,"tyre":"SM"},{"lap":1,"car":2,"sectors":[34375,26262,23261],"time":83898,"cuts":0,"tyre":"SM"},{"lap":2,"car":2,"sectors":[35635,27225,22518],"time":85378,"cuts":0,"tyre":"SM"},{"lap":3,"car":2,"sectors":[35479,26784,22329],"time":84592,"cuts":0,"tyre":"SM"},{"lap":4,"car":2,"sectors":[35510,27104,22212],"time":84826,"cuts":0,"tyre":"SM"},{"lap":5,"car":2,"sectors":[35610,27017,22348],"time":84975,"cuts":0,"tyre":"SM"},{"lap":6,"car":2,"sectors":[35936,27127,22338],"time":85401,"cuts":0,"tyre":"SM"},{"lap":7,"car":2,"sectors":[35927,27109,22302],"time":85338,"cuts":0,"tyre":"SM"},{"lap":8,"car":2,"sectors":[35882,27099,22266],"time":85247,"cuts":0,"tyre":"SM"},{"lap":9,"car":2,"sectors":[35827,27144,22225],"time":85196,"cuts":0,"tyre":"SM"},{"lap":0,"car":3,"sectors":[44286,25631,21726],"time":91643,"cuts":0,"tyre":"SM"},{"lap":1,"car":3,"sectors":[36002,26866,21987],"time":84855,"cuts":0,"tyre":"SM"},{"lap":2,"car":3,"sectors":[34604,25903,21779],"time":82286,"cuts":0,"tyre":"SM"},{"lap":3,"car":3,"sectors":[34909,26217,21730],"time":82856,"cuts":0,"tyre":"SM"},{"lap":4,"car":3,"sectors":[35314,26554,21992],"time":83860,"cuts":0,"tyre":"SM"},{"lap":5,"car":3,"sectors":[35686,26969,22383],"time":85038,"cuts":0,"tyre":"SM"},{"lap":6,"car":3,"sectors":[36238,27427,22879],"time":86544,"cuts":0,"tyre":"SM"},{"lap":7,"car":3,"sectors":[36728,27617,22806],"time":87151,"cuts":0,"tyre":"SM"},{"lap":8,"car":3,"sectors":[36469,27432,22631],"time":86532,"cuts":0,"tyre":"SM"},{"lap":9,"car":3,"sectors":[36639,27233,22451],"time":86323,"cuts":0,"tyre":"SM"},{"lap":0,"car":4,"sectors":[47670,26252,21726],"time":95648,"cuts":0,"tyre":"SM"},{"lap":1,"car":4,"sectors":[35993,27424,23229],"time":86646,"cuts":0,"tyre":"SM"},{"lap":2,"car":4,"sectors":[36427,28373,22806],"time":87606,"cuts":0,"tyre":"SM"},{"lap":3,"car":4,"sectors":[36215,27433,22621],"time":86269,"cuts":0,"tyre":"SM"},{"lap":4,"car":4,"sectors":[36185,27419,22541],"time":86145,"cuts":0,"tyre":"SM"},{"lap":5,"car":4,"sectors":[36472,27878,23876],"time":88226,"cuts":0,"tyre":"SM"},{"lap":6,"car":4,"sectors":[36066,27341,22550],"time":85957,"cuts":0,"tyre":"SM"},{"lap":7,"car":4,"sectors":[36276,28377,24191],"time":88844,"cuts":0,"tyre":"SM"},{"lap":8,"car":4,"sectors":[36308,27518,23108],"time":86934,"cuts":0,"tyre":"SM"},{"lap":9,"car":4,"sectors":[36616,28373,23498],"time":88487,"cuts":0,"tyre":"SM"},{"lap":0,"car":5,"sectors":[46571,25956,21492],"time":94019,"cuts":0,"tyre":"SM"},{"lap":1,"car":5,"sectors":[34472,26371,23112],"time":83955,"cuts":0,"tyre":"SM"},{"lap":2,"car":5,"sectors":[35829,27220,22311],"time":85360,"cuts":0,"tyre":"SM"},{"lap":3,"car":5,"sectors":[35681,27523,22428],"time":85632,"cuts":0,"tyre":"SM"},{"lap":4,"car":5,"sectors":[35559,26918,22446],"time":84923,"cuts":0,"tyre":"SM"},{"lap":5,"car":5,"sectors":[35998,27351,22482],"time":85831,"cuts":0,"tyre":"SM"},{"lap":6,"car":5,"sectors":[36424,27621,22698],"time":86743,"cuts":0,"tyre":"SM"},{"lap":7,"car":5,"sectors":[36555,27747,23413],"time":87715,"cuts":0,"tyre":"SM"},{"lap":8,"car":5,"sectors":[36707,27869,23575],"time":88151,"cuts":0,"tyre":"SM"},{"lap":9,"car":5,"sectors":[36794,28004,23071],"time":87869,"cuts":0,"tyre":"SM"},{"lap":0,"car":6,"sectors":[47309,26145,21682],"time":95136,"cuts":0,"tyre":"SM"},{"lap":1,"car":6,"sectors":[34771,26212,22969],"time":83952,"cuts":0,"tyre":"SM"},{"lap":2,"car":6,"sectors":[35388,27261,22797],"time":85446,"cuts":0,"tyre":"SM"},{"lap":3,"car":6,"sectors":[35748,27170,22429],"time":85347,"cuts":0,"tyre":"SM"},{"lap":4,"car":6,"sectors":[36458,27779,23665],"time":87902,"cuts":0,"tyre":"SM"},{"lap":5,"car":6,"sectors":[37038,28039,22995],"time":88072,"cuts":0,"tyre":"SM"},{"lap":6,"car":6,"sectors":[36802,27832,22788],"time":87422,"cuts":0,"tyre":"SM"},{"lap":7,"car":6,"sectors":[36623,27640,22626],"time":86889,"cuts":0,"tyre":"SM"},{"lap":8,"car":6,"sectors":[36477,27468,22540],"time":86485,"cuts":0,"tyre":"SM"},{"lap":9,"car":6,"sectors":[36474,27630,22679],"time":86783,"cuts":0,"tyre":"SM"},{"lap":0,"car":7,"sectors":[48034,26573,21563],"time":96170,"cuts":0,"tyre":"SM"},{"lap":1,"car":7,"sectors":[34679,26037,22771],"time":83487,"cuts":0,"tyre":"SM"},{"lap":2,"car":7,"sectors":[35171,27302,22909],"time":85382,"cuts":0,"tyre":"SM"},{"lap":3,"car":7,"sectors":[35584,27193,22631],"time":85408,"cuts":0,"tyre":"SM"},{"lap":4,"car":7,"sectors":[36222,27832,23810],"time":87864,"cuts":0,"tyre":"SM"},{"lap":5,"car":7,"sectors":[36841,28071,23211],"time":88123,"cuts":0,"tyre":"SM"},{"lap":6,"car":7,"sectors":[36852,28053,23571],"time":88476,"cuts":0,"tyre":"SM"},{"lap":7,"car":7,"sectors":[37134,28804,23967],"time":89905,"cuts":0,"tyre":"SM"},{"lap":8,"car":7,"sectors":[37670,28391,24003],"time":90064,"cuts":0,"tyre":"SM"},{"lap":9,"car":7,"sectors":[37603,28453,23999],"time":90055,"cuts":0,"tyre":"SM"},{"lap":0,"car":8,"sectors":[48421,26518,21771],"time":96710,"cuts":0,"tyre":"SM"},{"lap":1,"car":8,"sectors":[35269,27608,23183],"time":86060,"cuts":0,"tyre":"SM"},{"lap":2,"car":8,"sectors":[35823,27179,21916],"time":84918,"cuts":0,"tyre":"SM"},{"lap":3,"car":8,"sectors":[35756,27288,22293],"time":85337,"cuts":0,"tyre":"SM"},{"lap":4,"car":8,"sectors":[36309,27585,22608],"time":86502,"cuts":0,"tyre":"SM"},{"lap":5,"car":8,"sectors":[36558,27787,23139],"time":87484,"cuts":0,"tyre":"SM"},{"lap":6,"car":8,"sectors":[36699,28071,23660],"time":88430,"cuts":0,"tyre":"SM"},{"lap":7,"car":8,"sectors":[36957,28034,23027],"time":88018,"cuts":0,"tyre":"SM"},{"lap":8,"car":8,"sectors":[36797,27973,23494],"time":88264,"cuts":0,"tyre":"SM"},{"lap":9,"car":8,"sectors":[36843,28017,22940],"time":87800,"cuts":0,"tyre":"SM"},{"lap":0,"car":9,"sectors":[48790,26501,22000],"time":97291,"cuts":0,"tyre":"SM"},{"lap":1,"car":9,"sectors":[35020,27536,23489],"time":86045,"cuts":0,"tyre":"SM"},{"lap":2,"car":9,"sectors":[35733,27647,22253],"time":85633,"cuts":0,"tyre":"SM"},{"lap":3,"car":9,"sectors":[35835,27180,22382],"time":85397,"cuts":0,"tyre":"SM"},{"lap":4,"car":9,"sectors":[36525,27751,22878],"time":87154,"cuts":0,"tyre":"SM"},{"lap":5,"car":9,"sectors":[36901,27927,23661],"time":88489,"cuts":0,"tyre":"SM"},{"lap":6,"car":9,"sectors":[37409,28062,23774],"time":89245,"cuts":0,"tyre":"SM"},{"lap":7,"car":9,"sectors":[37103,27999,23693],"time":88795,"cuts":0,"tyre":"SM"},{"lap":8,"car":9,"sectors":[36991,27931,22910],"time":87832,"cuts":0,"tyre":"SM"},{"lap":9,"car":9,"sectors":[36942,28462,24161],"time":89565,"cuts":0,"tyre":"SM"},{"lap":0,"car":10,"sectors":[49154,26533,22153],"time":97840,"cuts":0,"tyre":"SM"},{"lap":1,"car":10,"sectors":[34817,27540,23689],"time":86046,"cuts":0,"tyre":"SM"},{"lap":2,"car":10,"sectors":[35653,27904,22968],"time":86525,"cuts":0,"tyre":"SM"},{"lap":3,"car":10,"sectors":[36038,27847,22337],"time":86222,"cuts":0,"tyre":"SM"},{"lap":4,"car":10,"sectors":[36047,27428,22766],"time":86241,"cuts":0,"tyre":"SM"},{"lap":5,"car":10,"sectors":[36359,27793,24101],"time":88253,"cuts":0,"tyre":"SM"},{"lap":6,"car":10,"sectors":[36713,28112,23855],"time":88680,"cuts":0,"tyre":"SM"},{"lap":7,"car":10,"sectors":[36940,28053,23809],"time":88802,"cuts":0,"tyre":"SM"},{"lap":8,"car":10,"sectors":[37028,28035,23517],"time":88580,"cuts":0,"tyre":"SM"},{"lap":9,"car":10,"sectors":[37227,28260,23611],"time":89098,"cuts":0,"tyre":"SM"}],"lapstotal":[10,10,10,10,10,10,10,10,10,10,10],"bestLaps":[{"car":0,"time":76733,"lap":9},{"car":1,"time":84463,"lap":7},{"car":2,"time":83898,"lap":1},{"car":3,"time":82286,"lap":2},{"car":4,"time":85957,"lap":6},{"car":5,"time":83955,"lap":1},{"car":6,"time":83952,"lap":1},{"car":7,"time":83487,"lap":1},{"car":8,"time":84918,"lap":2},{"car":9,"time":85397,"lap":3},{"car":10,"time":86046,"lap":1}],"raceResult":[0,1,3,2,5,6,8,4,7,9,10]}],"extras":[{"name":"bestlap","time":76733}],"__raceIni":"[HEADER]\r\nVERSION=2\r\n\r\n[RACE]\r\nTRACK=nemuno_ziedas\r\nCONFIG_TRACK=fastlap\r\nMODEL=ktm_xbow_r\r\nMODEL_CONFIG=\r\nCARS=11\r\nAI_LEVEL=100\r\nFIXED_SETUP=0\r\nPENALTIES=1\r\nSKIN=14_isotope_green_11\r\nDRIFT_MODE=0\r\nJUMP_START_PENALTY=0\r\nRACE_LAPS=10\r\n\r\n[REMOTE]\r\nACTIVE=0\r\nSERVER_IP=217.79.179.140\r\nSERVER_PORT=9779\r\nNAME=2m\r\nTEAM=\r\nGUID=76561198023763010\r\nREQUESTED_CAR=ford_transit\r\nPASSWORD=whitevanman\r\nSERVER_NAME=Chris Haye Sim Racing UK Server\r\nSERVER_HTTP_PORT=8779\r\n__CM_EXTENDED=0\r\n\r\n[CAR_0]\r\nSETUP=\r\nSKIN=14_isotope_green_11\r\nMODEL=-\r\nMODEL_CONFIG=\r\nBALLAST=0\r\nRESTRICTOR=0\r\nDRIVER_NAME=2m\r\nNATIONALITY=Lithuania\r\nNATION_CODE=LTU\r\n\r\n[GHOST_CAR]\r\nRECORDING=0\r\nPLAYING=0\r\nSECONDS_ADVANTAGE=0\r\nLOAD=0\r\nFILE=\r\nENABLED=0\r\n\r\n[REPLAY]\r\nFILENAME=\r\nACTIVE=0\r\n\r\n[LIGHTING]\r\nSUN_ANGLE=-15.21\r\nTIME_MULT=1.0\r\nCLOUD_SPEED=0.200\r\n__CM_WEATHER_TYPE=-1\r\n__TRACK_GEOTAG_LONG=23.70694\r\n__TRACK_TIMEZONE_BASE_OFFSET=7200\r\n__TRACK_TIMEZONE_DTS=0\r\n__TRACK_GEOTAG_LAT=54.91833\r\n__TRACK_TIMEZONE_OFFSET=7200\r\n\r\n[GROOVE]\r\nVIRTUAL_LAPS=10\r\nMAX_LAPS=30\r\nSTARTING_LAPS=0\r\n\r\n[DYNAMIC_TRACK]\r\nSESSION_START=200\r\nSESSION_TRANSFER=200\r\nRANDOMNESS=200\r\nLAP_GAIN=132\r\n\r\n[LAP_INVALIDATOR]\r\nALLOWED_TYRES_OUT=-1\r\n\r\n[TEMPERATURE]\r\nAMBIENT=28\r\nROAD=40\r\n\r\n[WEATHER]\r\nNAME=sol_02_few clouds\r\n\r\n[BENCHMARK]\r\nACTIVE=0\r\n\r\n[OPTIONS]\r\nUSE_MPH=0\r\n\r\n[SESSION_0]\r\nNAME=Quick Race\r\nDURATION_MINUTES=0\r\nSPAWN_SET=START\r\nTYPE=3\r\nLAPS=10\r\nSTARTING_POSITION=7\r\n\r\n[WIND]\r\nSPEED_KMH_MIN=6\r\nSPEED_KMH_MAX=6\r\nDIRECTION_DEG=0\r\n\r\n[CAR_10]\r\nMODEL=ktm_xbow_r\r\nSKIN=13_light_grey_08\r\nSETUP=\r\nMODEL_CONFIG=\r\nAI_LEVEL=77.6\r\nAI_AGGRESSION=19.9\r\nDRIVER_NAME=Giorgio Chiarcossi\r\nBALLAST=0\r\nRESTRICTOR=0\r\nNATION_CODE=ITA\r\nNATIONALITY=Italy\r\n\r\n[CAR_9]\r\nMODEL=ktm_xbow_r\r\nSKIN=01_blue_01\r\nSETUP=\r\nMODEL_CONFIG=\r\nAI_LEVEL=78.6\r\nAI_AGGRESSION=20.9\r\nDRIVER_NAME=Philippe Jamoul\r\nBALLAST=0\r\nRESTRICTOR=0\r\nNATION_CODE=BEL\r\nNATIONALITY=Belgium\r\n\r\n[CAR_8]\r\nMODEL=ktm_xbow_r\r\nSKIN=16_light_grey_13\r\nSETUP=\r\nMODEL_CONFIG=\r\nAI_LEVEL=79.6\r\nAI_AGGRESSION=21.9\r\nDRIVER_NAME=Romain Rouhaud\r\nBALLAST=0\r\nRESTRICTOR=0\r\nNATION_CODE=FRA\r\nNATIONALITY=France\r\n\r\n[CAR_7]\r\nMODEL=ktm_xbow_r\r\nSKIN=12_cyan_05\r\nSETUP=\r\nMODEL_CONFIG=\r\nAI_LEVEL=78.6\r\nAI_AGGRESSION=23.9\r\nDRIVER_NAME=Bernard Bensimon\r\nBALLAST=0\r\nRESTRICTOR=0\r\nNATION_CODE=FRA\r\nNATIONALITY=France\r\n\r\n[CAR_6]\r\nMODEL=ktm_xbow_r\r\nSKIN=02_isotope_green_10\r\nSETUP=\r\nMODEL_CONFIG=\r\nAI_LEVEL=79.6\r\nAI_AGGRESSION=22.9\r\nDRIVER_NAME=Alain Camilli\r\nBALLAST=0\r\nRESTRICTOR=0\r\nNATION_CODE=FRA\r\nNATIONALITY=France\r\n\r\n[CAR_5]\r\nMODEL=ktm_xbow_r\r\nSKIN=08_orange_19\r\nSETUP=\r\nMODEL_CONFIG=\r\nAI_LEVEL=80.6\r\nAI_AGGRESSION=24.9\r\nDRIVER_NAME=Eerik Tuohino\r\nBALLAST=0\r\nRESTRICTOR=0\r\nNATION_CODE=FIN\r\nNATIONALITY=Finland\r\n\r\n[CAR_4]\r\nMODEL=ktm_xbow_r\r\nSKIN=04_yellow_07\r\nSETUP=\r\nMODEL_CONFIG=\r\nAI_LEVEL=80.6\r\nAI_AGGRESSION=23.9\r\nDRIVER_NAME=Jeff LeBeau\r\nBALLAST=0\r\nRESTRICTOR=0\r\nNATION_CODE=USA\r\nNATIONALITY=USA\r\n\r\n[CAR_3]\r\nMODEL=ktm_xbow_r\r\nSKIN=03_dark_grey_06\r\nSETUP=\r\nMODEL_CONFIG=\r\nAI_LEVEL=81.6\r\nAI_AGGRESSION=25.9\r\nDRIVER_NAME=Max Saarinen\r\nBALLAST=0\r\nRESTRICTOR=0\r\nNATION_CODE=FIN\r\nNATIONALITY=Finland\r\n\r\n[CAR_2]\r\nMODEL=ktm_xbow_r\r\nSKIN=10_blue_02\r\nSETUP=\r\nMODEL_CONFIG=\r\nAI_LEVEL=81.6\r\nAI_AGGRESSION=27.9\r\nDRIVER_NAME=Mohammed Al-Qassimi\r\nBALLAST=0\r\nRESTRICTOR=0\r\nNATION_CODE=UAE\r\nNATIONALITY=UAE\r\n\r\n[CAR_1]\r\nMODEL=ktm_xbow_r\r\nSKIN=07_dark_grey_09\r\nSETUP=\r\nMODEL_CONFIG=\r\nAI_LEVEL=82.6\r\nAI_AGGRESSION=26.9\r\nDRIVER_NAME=Michael Martin\r\nBALLAST=0\r\nRESTRICTOR=0\r\nNATION_CODE=USA\r\nNATIONALITY=USA\r\n\r\n","__quickDrive":"{\"Mode\":\"/Pages/Drive/QuickDrive_Race.xaml\",\"ModeData\":\"{\\\"Penalties\\\":true,\\\"JumpStartPenalty\\\":0,\\\"LapsNumber\\\":10,\\\"RaceGridSerialized\\\":\\\"{\\\\\\\"ModeId\\\\\\\":\\\\\\\"same_car\\\\\\\",\\\\\\\"FilterValue\\\\\\\":\\\\\\\"\\\\\\\",\\\\\\\"CarIds\\\\\\\":[\\\\\\\"ktm_xbow_r\\\\\\\"],\\\\\\\"ShuffleCandidates\\\\\\\":true,\\\\\\\"VarietyLimitation\\\\\\\":0,\\\\\\\"OpponentsNumber\\\\\\\":10,\\\\\\\"StartingPosition\\\\\\\":7,\\\\\\\"AiLevel\\\\\\\":82.5,\\\\\\\"AiLevelMin\\\\\\\":77.600000000000009,\\\\\\\"AiLevelArrangeRandom\\\\\\\":0.1,\\\\\\\"AiLevelArrangeReverse\\\\\\\":false,\\\\\\\"AiAggression\\\\\\\":27.8,\\\\\\\"AiAggressionMin\\\\\\\":19.900000000000002,\\\\\\\"AiAggressionArrangeRandom\\\\\\\":0.1,\\\\\\\"AiAggressionArrangeReverse\\\\\\\":false}\\\",\\\"Version\\\":2}\",\"CarId\":\"ktm_xbow_r\",\"TrackId\":\"nemuno_ziedas/fastlap\",\"WeatherId\":\"sol_02_Few Clouds\",\"RealConditions\":false,\"Temperature\":28.0,\"Time\":43377,\"TimeMultipler\":1,\"udt\":false,\"dtv\":\"2018-11-10T17:30:05.3536382+02:00\",\"tpc\":false,\"TrackPropertiesPresetFilename\":\"C:\\\\Users\\\\Martynas\\\\AppData\\\\Local\\\\AcTools Content Manager\\\\Presets\\\\Track States\\\\Green.cmpreset\",\"TrackPropertiesData\":\"{\\\"s\\\":2.0,\\\"t\\\":2.0,\\\"r\\\":2.0,\\\"g\\\":132,\\\"w\\\":false}\",\"asc\":true,\"AssistsPresetFilename\":\"C:\\\\Users\\\\Martynas\\\\AppData\\\\Local\\\\AcTools Content Manager\\\\Presets\\\\Assists\\\\Pro.cmpreset\",\"AssistsData\":\"{\\\"IdealLine\\\":false,\\\"AutoBlip\\\":false,\\\"StabilityControl\\\":0.0,\\\"AutoBrake\\\":false,\\\"AutoShifter\\\":false,\\\"SlipSteam\\\":1.0,\\\"AutoClutch\\\":false,\\\"Abs\\\":1,\\\"TractionControl\\\":1,\\\"VisualDamage\\\":true,\\\"Damage\\\":100.0,\\\"TyreWear\\\":1.0,\\\"FuelConsumption\\\":1.0,\\\"TyreBlankets\\\":true}\",\"ico\":false,\"wsf\":6.0,\"wst\":6.0,\"wd\":0.0,\"rws\":false,\"rwd\":false,\"rcTimezones\":true,\"rcManTime\":false,\"rcManWind\":false,\"rcLw\":false,\"rte\":false,\"rti\":false,\"crt\":false}"}